repocollector/__init__.py
repocollector/cli.py
repocollector/github.py
repocollector/report.py
repositories_collector-0.0.5.dist-info/LICENSE
repositories_collector-0.0.5.dist-info/METADATA
repositories_collector-0.0.5.dist-info/WHEEL
repositories_collector-0.0.5.dist-info/entry_points.txt
repositories_collector-0.0.5.dist-info/top_level.txt
repositories_collector-0.0.5.dist-info/RECORD
