Metadata-Version: 2.1
Name: repositories-collector
Version: 0.0.5
Summary: A tool to query GraphQL for collecting repositories metadata.
Home-page: https://github.com/radon-h2020/radon-repositories-collector
Author: Stefano Dalla Palma
Author-email: stefano.dallapalma0@gmail.com
Maintainer: Stefano Dalla Palma
License: UNKNOWN
Download-URL: https://github.com/radon-h2020/radon-repositories-collector/archive/0.0.5.tar.gz
Platform: UNKNOWN
Classifier: Development Status :: 5 - Production/Stable
Classifier: Intended Audience :: Developers
Classifier: Programming Language :: Python :: 3.7
Classifier: License :: OSI Approved :: Apache Software License
Classifier: Topic :: Software Development :: Libraries :: Python Modules
Classifier: Operating System :: OS Independent
License-File: LICENSE
Requires-Dist: requests (~=2.24.0)
